client/__init__.py
client/add_contact.py
client/client_db.py
client/del_contact.py
client/main_window.py
client/main_window_conv.py
client/start_dialog.py
client/transport.py
common/__init__.py
common/decos.py
common/descryptors.py
common/errors.py
common/log_decorator.py
common/metaclasses.py
common/utils.py
common/variables.py
doc/__init__.py
doc/source/__init__.py
doc/source/conf.py
logs/__init__.py
logs/config_client_log.py
logs/config_server_log.py
unit_tests/__init__.py
unit_tests/test_client.py
unit_tests/test_server.py
unit_tests/test_utils.py
messanger_lite_client-1.0.1.dist-info/LICENSE.txt
messanger_lite_client-1.0.1.dist-info/METADATA
messanger_lite_client-1.0.1.dist-info/WHEEL
messanger_lite_client-1.0.1.dist-info/top_level.txt
messanger_lite_client-1.0.1.dist-info/RECORD
