Metadata-Version: 2.1
Name: messanger-lite-client
Version: 1.0.1
Summary: messanger_lite_client
Author: Idel Yusupov
Author-email: idel@mail.ru
License: UNKNOWN
Platform: UNKNOWN
License-File: LICENSE.txt
Requires-Dist: PyQt5
Requires-Dist: sqlalchemy
Requires-Dist: pycryptodome
Requires-Dist: pycryptodomex
